usrak/__init__.py
usrak/auth_app.py
usrak/auth_router.py
usrak/providers_type.py
usrak/remote_address.py
usrak/core/__init__.py
usrak/core/config_schemas.py
usrak/core/db.py
usrak/core/enums.py
usrak/core/google.py
usrak/core/limiter_identifiers.py
usrak/core/logger.py
usrak/core/security.py
usrak/core/_rate_limit/__init__.py
usrak/core/_rate_limit/base.py
usrak/core/_rate_limit/mail_code.py
usrak/core/_rate_limit/mail_link.py
usrak/core/dependencies/__init__.py
usrak/core/dependencies/admin.py
usrak/core/dependencies/config_provider.py
usrak/core/dependencies/limiters.py
usrak/core/dependencies/managers.py
usrak/core/dependencies/user.py
usrak/core/exceptions/__init__.py
usrak/core/exceptions/auth.py
usrak/core/exceptions/internal.py
usrak/core/exceptions/oauth.py
usrak/core/exceptions/server.py
usrak/core/exceptions/user.py
usrak/core/handlers/__init__.py
usrak/core/handlers/excpetion.py
usrak/core/managers/__init__.py
usrak/core/managers/password_reset.py
usrak/core/managers/key_value_store/__init__.py
usrak/core/managers/key_value_store/base.py
usrak/core/managers/key_value_store/in_memory.py
usrak/core/managers/key_value_store/lmdb_store.py
usrak/core/managers/key_value_store/redis_store.py
usrak/core/managers/notification/__init__.py
usrak/core/managers/notification/base.py
usrak/core/managers/notification/no_op.py
usrak/core/managers/notification/smtp.py
usrak/core/managers/password_reset/__init__.py
usrak/core/managers/password_reset/base.py
usrak/core/managers/password_reset/mail.py
usrak/core/managers/rate_limiter/__init__.py
usrak/core/managers/rate_limiter/interface.py
usrak/core/managers/rate_limiter/no_op.py
usrak/core/managers/rate_limiter/redis.py
usrak/core/managers/sign_up/__init__.py
usrak/core/managers/sign_up/admin.py
usrak/core/managers/sign_up/base.py
usrak/core/managers/sign_up/mail.py
usrak/core/managers/sign_up/no_op.py
usrak/core/managers/tokens/__init__.py
usrak/core/managers/tokens/auth.py
usrak/core/managers/tokens/base.py
usrak-0.2.3.dist-info/METADATA
usrak-0.2.3.dist-info/WHEEL
usrak-0.2.3.dist-info/top_level.txt
usrak-0.2.3.dist-info/RECORD
